{
  "events": [
    {
      "id": 123,
      "category": "animal welfare",
      "title": "Cat Adoption Day",
      "description": "Find your new feline friend at this event.",
      "location": "Meow Town",
      "date": "January 28, 2022",
      "time": "12:00",
      "organizer": "Kat Laydee"
    },
    {
      "id": 456,
      "category": "food",
      "title": "Community Gardening",
      "description": "Join us as we tend to the community edible plants.",
      "location": "Flora City",
      "date": "March 14, 2022",
      "time": "10:00",
      "organizer": "Fern Pollin"
    },
    {
      "id": 789,
      "category": "sustainability",
      "title": "Beach Cleanup",
      "description": "Help pick up trash along the shore.",
      "location": "Playa Del Carmen",
      "date": "July 22, 2022",
      "time": "11:00",
      "organizer": "Carey Wales"
    },
    {
      "id": 1230,
      "category": "animal welfare",
      "title": "Cat Adoption Day",
      "description": "Find your new feline friend at this event.",
      "location": "Meow Town",
      "date": "January 28, 2022",
      "time": "12:00",
      "organizer": "Kat Laydee"
    },
    {
      "id": 4560,
      "category": "food",
      "title": "Community Gardening",
      "description": "Join us as we tend to the community edible plants.",
      "location": "Flora City",
      "date": "March 14, 2022",
      "time": "10:00",
      "organizer": "Fern Pollin"
    },
    {
      "id": 7890,
      "category": "sustainability",
      "title": "Beach Cleanup",
      "description": "Help pick up trash along the shore.",
      "location": "Playa Del Carmen",
      "date": "July 22, 2022",
      "time": "11:00",
      "organizer": "Carey Wales"
    },
    {
      "id": 1231,
      "category": "animal welfare",
      "title": "Cat Adoption Day",
      "description": "Find your new feline friend at this event.",
      "location": "Meow Town",
      "date": "January 28, 2022",
      "time": "12:00",
      "organizer": "Kat Laydee"
    },
    {
      "id": 4561,
      "category": "food",
      "title": "Community Gardening",
      "description": "Join us as we tend to the community edible plants.",
      "location": "Flora City",
      "date": "March 14, 2022",
      "time": "10:00",
      "organizer": "Fern Pollin"
    },
    {
      "id": 7891,
      "category": "sustainability",
      "title": "Beach Cleanup",
      "description": "Help pick up trash along the shore.",
      "location": "Playa Del Carmen",
      "date": "July 22, 2022",
      "time": "11:00",
      "organizer": "Carey Wales"
    },
    {
      "id": 12301,
      "category": "animal welfare",
      "title": "Cat Adoption Day",
      "description": "Find your new feline friend at this event.",
      "location": "Meow Town",
      "date": "January 28, 2022",
      "time": "12:00",
      "organizer": "Kat Laydee"
    },
    {
      "id": 45601,
      "category": "food",
      "title": "Community Gardening",
      "description": "Join us as we tend to the community edible plants.",
      "location": "Flora City",
      "date": "March 14, 2022",
      "time": "10:00",
      "organizer": "Fern Pollin"
    },
    {
      "id": 78901,
      "category": "sustainability",
      "title": "Beach Cleanup",
      "description": "Help pick up trash along the shore.",
      "location": "Playa Del Carmen",
      "date": "July 22, 2022",
      "time": "11:00",
      "organizer": "Carey Wales"
    },
    {
      "id": 1232,
      "category": "animal welfare",
      "title": "Cat Adoption Day",
      "description": "Find your new feline friend at this event.",
      "location": "Meow Town",
      "date": "January 28, 2022",
      "time": "12:00",
      "organizer": "Kat Laydee"
    },
    {
      "id": 4562,
      "category": "food",
      "title": "Community Gardening",
      "description": "Join us as we tend to the community edible plants.",
      "location": "Flora City",
      "date": "March 14, 2022",
      "time": "10:00",
      "organizer": "Fern Pollin"
    },
    {
      "id": 7892,
      "category": "sustainability",
      "title": "Beach Cleanup",
      "description": "Help pick up trash along the shore.",
      "location": "Playa Del Carmen",
      "date": "July 22, 2022",
      "time": "11:00",
      "organizer": "Carey Wales"
    },
    {
      "id": 12302,
      "category": "animal welfare",
      "title": "Cat Adoption Day",
      "description": "Find your new feline friend at this event.",
      "location": "Meow Town",
      "date": "January 28, 2022",
      "time": "12:00",
      "organizer": "Kat Laydee"
    },
    {
      "id": 45602,
      "category": "food",
      "title": "Community Gardening",
      "description": "Join us as we tend to the community edible plants.",
      "location": "Flora City",
      "date": "March 14, 2022",
      "time": "10:00",
      "organizer": "Fern Pollin"
    },
    {
      "id": 78902,
      "category": "sustainability",
      "title": "Beach Cleanup",
      "description": "Help pick up trash along the shore.",
      "location": "Playa Del Carmen",
      "date": "July 22, 2022",
      "time": "11:00",
      "organizer": "Carey Wales"
    },
    {
      "id": 12312,
      "category": "animal welfare",
      "title": "Cat Adoption Day",
      "description": "Find your new feline friend at this event.",
      "location": "Meow Town",
      "date": "January 28, 2022",
      "time": "12:00",
      "organizer": "Kat Laydee"
    },
    {
      "id": 45612,
      "category": "food",
      "title": "Community Gardening",
      "description": "Join us as we tend to the community edible plants.",
      "location": "Flora City",
      "date": "March 14, 2022",
      "time": "10:00",
      "organizer": "Fern Pollin"
    },
    {
      "id": 78912,
      "category": "sustainability",
      "title": "Beach Cleanup",
      "description": "Help pick up trash along the shore.",
      "location": "Playa Del Carmen",
      "date": "July 22, 2022",
      "time": "11:00",
      "organizer": "Carey Wales"
    },
    {
      "id": 123012,
      "category": "animal welfare",
      "title": "Cat Adoption Day",
      "description": "Find your new feline friend at this event.",
      "location": "Meow Town",
      "date": "January 28, 2022",
      "time": "12:00",
      "organizer": "Kat Laydee"
    },
    {
      "id": 456012,
      "category": "food",
      "title": "Community Gardening",
      "description": "Join us as we tend to the community edible plants.",
      "location": "Flora City",
      "date": "March 14, 2022",
      "time": "10:00",
      "organizer": "Fern Pollin"
    },
    {
      "id": 789012,
      "category": "sustainability",
      "title": "Beach Cleanup",
      "description": "Help pick up trash along the shore.",
      "location": "Playa Del Carmen",
      "date": "July 22, 2022",
      "time": "11:00",
      "organizer": "Carey Wales"
    },
    {
      "id": 1239,
      "category": "animal welfare",
      "title": "Cat Adoption Day",
      "description": "Find your new feline friend at this event.",
      "location": "Meow Town",
      "date": "January 28, 2022",
      "time": "12:00",
      "organizer": "Kat Laydee"
    },
    {
      "id": 4569,
      "category": "food",
      "title": "Community Gardening",
      "description": "Join us as we tend to the community edible plants.",
      "location": "Flora City",
      "date": "March 14, 2022",
      "time": "10:00",
      "organizer": "Fern Pollin"
    },
    {
      "id": 7899,
      "category": "sustainability",
      "title": "Beach Cleanup",
      "description": "Help pick up trash along the shore.",
      "location": "Playa Del Carmen",
      "date": "July 22, 2022",
      "time": "11:00",
      "organizer": "Carey Wales"
    },
    {
      "id": 12309,
      "category": "animal welfare",
      "title": "Cat Adoption Day",
      "description": "Find your new feline friend at this event.",
      "location": "Meow Town",
      "date": "January 28, 2022",
      "time": "12:00",
      "organizer": "Kat Laydee"
    },
    {
      "id": 45609,
      "category": "food",
      "title": "Community Gardening",
      "description": "Join us as we tend to the community edible plants.",
      "location": "Flora City",
      "date": "March 14, 2022",
      "time": "10:00",
      "organizer": "Fern Pollin"
    },
    {
      "id": 78909,
      "category": "sustainability",
      "title": "Beach Cleanup",
      "description": "Help pick up trash along the shore.",
      "location": "Playa Del Carmen",
      "date": "July 22, 2022",
      "time": "11:00",
      "organizer": "Carey Wales"
    },
    {
      "id": 12319,
      "category": "animal welfare",
      "title": "Cat Adoption Day",
      "description": "Find your new feline friend at this event.",
      "location": "Meow Town",
      "date": "January 28, 2022",
      "time": "12:00",
      "organizer": "Kat Laydee"
    },
    {
      "id": 45619,
      "category": "food",
      "title": "Community Gardening",
      "description": "Join us as we tend to the community edible plants.",
      "location": "Flora City",
      "date": "March 14, 2022",
      "time": "10:00",
      "organizer": "Fern Pollin"
    },
    {
      "id": 78919,
      "category": "sustainability",
      "title": "Beach Cleanup",
      "description": "Help pick up trash along the shore.",
      "location": "Playa Del Carmen",
      "date": "July 22, 2022",
      "time": "11:00",
      "organizer": "Carey Wales"
    },
    {
      "id": 123019,
      "category": "animal welfare",
      "title": "Cat Adoption Day",
      "description": "Find your new feline friend at this event.",
      "location": "Meow Town",
      "date": "January 28, 2022",
      "time": "12:00",
      "organizer": "Kat Laydee"
    },
    {
      "id": 456019,
      "category": "food",
      "title": "Community Gardening",
      "description": "Join us as we tend to the community edible plants.",
      "location": "Flora City",
      "date": "March 14, 2022",
      "time": "10:00",
      "organizer": "Fern Pollin"
    },
    {
      "id": 789019,
      "category": "sustainability",
      "title": "Beach Cleanup",
      "description": "Help pick up trash along the shore.",
      "location": "Playa Del Carmen",
      "date": "July 22, 2022",
      "time": "11:00",
      "organizer": "Carey Wales"
    },
    {
      "id": 12329,
      "category": "animal welfare",
      "title": "Cat Adoption Day",
      "description": "Find your new feline friend at this event.",
      "location": "Meow Town",
      "date": "January 28, 2022",
      "time": "12:00",
      "organizer": "Kat Laydee"
    },
    {
      "id": 45629,
      "category": "food",
      "title": "Community Gardening",
      "description": "Join us as we tend to the community edible plants.",
      "location": "Flora City",
      "date": "March 14, 2022",
      "time": "10:00",
      "organizer": "Fern Pollin"
    },
    {
      "id": 78929,
      "category": "sustainability",
      "title": "Beach Cleanup",
      "description": "Help pick up trash along the shore.",
      "location": "Playa Del Carmen",
      "date": "July 22, 2022",
      "time": "11:00",
      "organizer": "Carey Wales"
    },
    {
      "id": 123029,
      "category": "animal welfare",
      "title": "Cat Adoption Day",
      "description": "Find your new feline friend at this event.",
      "location": "Meow Town",
      "date": "January 28, 2022",
      "time": "12:00",
      "organizer": "Kat Laydee"
    },
    {
      "id": 456029,
      "category": "food",
      "title": "Community Gardening",
      "description": "Join us as we tend to the community edible plants.",
      "location": "Flora City",
      "date": "March 14, 2022",
      "time": "10:00",
      "organizer": "Fern Pollin"
    },
    {
      "id": 789029,
      "category": "sustainability",
      "title": "Beach Cleanup",
      "description": "Help pick up trash along the shore.",
      "location": "Playa Del Carmen",
      "date": "July 22, 2022",
      "time": "11:00",
      "organizer": "Carey Wales"
    },
    {
      "id": 123129,
      "category": "animal welfare",
      "title": "Cat Adoption Day",
      "description": "Find your new feline friend at this event.",
      "location": "Meow Town",
      "date": "January 28, 2022",
      "time": "12:00",
      "organizer": "Kat Laydee"
    },
    {
      "id": 456129,
      "category": "food",
      "title": "Community Gardening",
      "description": "Join us as we tend to the community edible plants.",
      "location": "Flora City",
      "date": "March 14, 2022",
      "time": "10:00",
      "organizer": "Fern Pollin"
    },
    {
      "id": 789129,
      "category": "sustainability",
      "title": "Beach Cleanup",
      "description": "Help pick up trash along the shore.",
      "location": "Playa Del Carmen",
      "date": "July 22, 2022",
      "time": "11:00",
      "organizer": "Carey Wales"
    },
    {
      "id": 1230129,
      "category": "animal welfare",
      "title": "Cat Adoption Day",
      "description": "Find your new feline friend at this event.",
      "location": "Meow Town",
      "date": "January 28, 2022",
      "time": "12:00",
      "organizer": "Kat Laydee"
    },
    {
      "id": 4560129,
      "category": "food",
      "title": "Community Gardening",
      "description": "Join us as we tend to the community edible plants.",
      "location": "Flora City",
      "date": "March 14, 2022",
      "time": "10:00",
      "organizer": "Fern Pollin"
    },
    {
      "id": 7890129,
      "category": "sustainability",
      "title": "Beach Cleanup",
      "description": "Help pick up trash along the shore.",
      "location": "Playa Del Carmen",
      "date": "July 22, 2022",
      "time": "11:00",
      "organizer": "Carey Wales"
    }
  ]
}
